translate_po/__init__.py
translate_po/main.py
translate_po/utilities/__init__.py
translate_po/utilities/constants.py
translate_po/utilities/io.py
translate_po/utilities/match.py
translate_po-1.0.13.dist-info/LICENSE
translate_po-1.0.13.dist-info/METADATA
translate_po-1.0.13.dist-info/WHEEL
translate_po-1.0.13.dist-info/entry_points.txt
translate_po-1.0.13.dist-info/top_level.txt
translate_po-1.0.13.dist-info/RECORD
