Metadata-Version: 2.1
Name: translate-po
Version: 1.0.13
Summary: Automatic PO file translator
Home-page: https://github.com/zcribe/translate-po
Author: Erlend Eelmets
Author-email: erlend.eelmets@gmail.com
License: UNKNOWN
Project-URL: Source, https://github.com/zcribe/translate-po
Project-URL: Documentation, https://github.com/zcribe/translate-po/docs/main.html
Project-URL: Author, http://www.erlend.ee
Keywords: po translate automatic google
Platform: UNKNOWN
Classifier: Development Status :: 3 - Alpha
Classifier: Programming Language :: Python :: 3
Classifier: License :: OSI Approved :: MIT License
Classifier: Operating System :: OS Independent
Classifier: Intended Audience :: Developers
Classifier: Topic :: Software Development :: Internationalization
Requires-Python: >=3.6
Requires-Dist: polib (>=1.1.0)
Requires-Dist: googletrans (>=3.0.0)
